counter/synchronous/design.sv
// Code your design here
module four_bit_synchronous_counter
  (
    input logic clk,rstn,up_down,
    output logic [3:0] count
  );
  always_ff @(posedge clk)begin
    if (!rstn) count <=0;
    else if (up_down ==0) begin
      count<= count +1'b1;
    end else if (up_down ==1) begin
      count<= count -1'b1;
    end
  end
endmodule

counter/synchronous/testbench.sv
// Code your testbench here
// or browse Examples
`timescale 1ns/1ps
module syncronous_counter_tb;
  logic clk=0;
  logic rstn =1;
  logic up_down;
  logic [3:0] count;
  
  four_bit_synchronous_counter dut(.*);  
  
  localparam clk_period =10;
  initial begin 
    forever #(clk_period/2)clk<=~clk;
  end
  
  initial begin
    $dumpfile("dump.vcd");
    $dumpvars(0,dut);
    #1 rstn<=0;
    #6 rstn<=1;
    #1up_down<=0;
    #1000 $finish();
  end
endmodule

counter/synchronous/dump.vcd
$date
	Wed Oct 16 14:49:30 2024
$end
$version
	Icarus Verilog
$end
$timescale
	1ps
$end
$scope module syncronous_counter_tb $end
$scope module dut $end
$var wire 1 ! clk $end
$var wire 1 " rstn $end
$var wire 1 # up_down $end
$var reg 4 $ count [3:0] $end
$upscope $end
$upscope $end
$enddefinitions $end
$comment Show the parameter values. $end
$dumpall
$end
#0
$dumpvars
bx $
x#
1"
0!
$end
#1000
0"
#5000
b0 $
1!
#7000
1"
#8000
0#
#10000
0!
#15000
b1 $
1!
#20000
0!
#25000
b10 $
1!
#30000
0!
#35000
b11 $
1!
#40000
0!
#45000
b100 $
1!
#50000
0!
#55000
b101 $
1!
#60000
0!
#65000
b110 $
1!
#70000
0!
#75000
b111 $
1!
#80000
0!
#85000
b1000 $
1!
#90000
0!
#95000
b1001 $
1!
#100000
0!
#105000
b1010 $
1!
#110000
0!
#115000
b1011 $
1!
#120000
0!
#125000
b1100 $
1!
#130000
0!
#135000
b1101 $
1!
#140000
0!
#145000
b1110 $
1!
#150000
0!
#155000
b1111 $
1!
#160000
0!
#165000
b0 $
1!
#170000
0!
#175000
b1 $
1!
#180000
0!
#185000
b10 $
1!
#190000
0!
#195000
b11 $
1!
#200000
0!
#205000
b100 $
1!
#210000
0!
#215000
b101 $
1!
#220000
0!
#225000
b110 $
1!
#230000
0!
#235000
b111 $
1!
#240000
0!
#245000
b1000 $
1!
#250000
0!
#255000
b1001 $
1!
#260000
0!
#265000
b1010 $
1!
#270000
0!
#275000
b1011 $
1!
#280000
0!
#285000
b1100 $
1!
#290000
0!
#295000
b1101 $
1!
#300000
0!
#305000
b1110 $
1!
#310000
0!
#315000
b1111 $
1!
#320000
0!
#325000
b0 $
1!
#330000
0!
#335000
b1 $
1!
#340000
0!
#345000
b10 $
1!
#350000
0!
#355000
b11 $
1!
#360000
0!
#365000
b100 $
1!
#370000
0!
#375000
b101 $
1!
#380000
0!
#385000
b110 $
1!
#390000
0!
#395000
b111 $
1!
#400000
0!
#405000
b1000 $
1!
#410000
0!
#415000
b1001 $
1!
#420000
0!
#425000
b1010 $
1!
#430000
0!
#435000
b1011 $
1!
#440000
0!
#445000
b1100 $
1!
#450000
0!
#455000
b1101 $
1!
#460000
0!
#465000
b1110 $
1!
#470000
0!
#475000
b1111 $
1!
#480000
0!
#485000
b0 $
1!
#490000
0!
#495000
b1 $
1!
#500000
0!
#505000
b10 $
1!
#510000
0!
#515000
b11 $
1!
#520000
0!
#525000
b100 $
1!
#530000
0!
#535000
b101 $
1!
#540000
0!
#545000
b110 $
1!
#550000
0!
#555000
b111 $
1!
#560000
0!
#565000
b1000 $
1!
#570000
0!
#575000
b1001 $
1!
#580000
0!
#585000
b1010 $
1!
#590000
0!
#595000
b1011 $
1!
#600000
0!
#605000
b1100 $
1!
#610000
0!
#615000
b1101 $
1!
#620000
0!
#625000
b1110 $
1!
#630000
0!
#635000
b1111 $
1!
#640000
0!
#645000
b0 $
1!
#650000
0!
#655000
b1 $
1!
#660000
0!
#665000
b10 $
1!
#670000
0!
#675000
b11 $
1!
#680000
0!
#685000
b100 $
1!
#690000
0!
#695000
b101 $
1!
#700000
0!
#705000
b110 $
1!
#710000
0!
#715000
b111 $
1!
#720000
0!
#725000
b1000 $
1!
#730000
0!
#735000
b1001 $
1!
#740000
0!
#745000
b1010 $
1!
#750000
0!
#755000
b1011 $
1!
#760000
0!
#765000
b1100 $
1!
#770000
0!
#775000
b1101 $
1!
#780000
0!
#785000
b1110 $
1!
#790000
0!
#795000
b1111 $
1!
#800000
0!
#805000
b0 $
1!
#810000
0!
#815000
b1 $
1!
#820000
0!
#825000
b10 $
1!
#830000
0!
#835000
b11 $
1!
#840000
0!
#845000
b100 $
1!
#850000
0!
#855000
b101 $
1!
#860000
0!
#865000
b110 $
1!
#870000
0!
#875000
b111 $
1!
#880000
0!
#885000
b1000 $
1!
#890000
0!
#895000
b1001 $
1!
#900000
0!
#905000
b1010 $
1!
#910000
0!
#915000
b1011 $
1!
#920000
0!
#925000
b1100 $
1!
#930000
0!
#935000
b1101 $
1!
#940000
0!
#945000
b1110 $
1!
#950000
0!
#955000
b1111 $
1!
#960000
0!
#965000
b0 $
1!
#970000
0!
#975000
b1 $
1!
#980000
0!
#985000
b10 $
1!
#990000
0!
#995000
b11 $
1!
#1000000
0!
#1005000
b100 $
1!
